FAALpy/Alignment.py
FAALpy/ConfigIPA.py
FAALpy/IPA_Parser.py
FAALpy/Matcher.py
FAALpy/MatcherConfig1.py
FAALpy/MatcherConfig2.py
FAALpy/MatcherConfig3.py
FAALpy/MatcherConfig4.py
FAALpy/ParsedWord.py
FAALpy/Reader.py
FAALpy/ThreadAfterMax.py
FAALpy/ThreadBeforeMax.py
FAALpy/ThreadInitialSeq.py
FAALpy/ThreadTailSeq.py
FAALpy/__init__.py
FAALpy/config/__init__.py
FAALpy/config/external_corr_glob_sim_score_function.txt
FAALpy/config/features_coarticulation.txt
FAALpy/config/features_diphthongs.txt
FAALpy/config/phon_categories.txt
FAALpy/config/phon_diacritics.txt
FAALpy/config/phon_features.txt
FAALpy/config/saliences_to_use_matches_phon_categories.txt
FAALpy/config/saliences/__init__.py
FAALpy/config/saliences/salience_cat_1.txt
FAALpy/config/saliences/salience_cat_2.txt
FAALpy/config/saliences/salience_cat_3.txt
FAALpy-0.1.4.dist-info/LICENCE.txt
FAALpy-0.1.4.dist-info/METADATA
FAALpy-0.1.4.dist-info/WHEEL
FAALpy-0.1.4.dist-info/top_level.txt
FAALpy-0.1.4.dist-info/RECORD
