Metadata-Version: 2.1
Name: FAALpy
Version: 0.1.4
Summary: A python version of the .jar library FAAL
Home-page: https://github.com/MKilani/FAALpy
Author: Marwan Kilani
Author-email: kilani.edu@gmail.com
License: MIT
Platform: UNKNOWN
Classifier: Programming Language :: Python :: 3
Classifier: License :: OSI Approved :: MIT License
Classifier: Operating System :: OS Independent
Requires-Python: >=3.0
License-File: LICENCE.txt
Requires-Dist: numexpr
